tensordock/__init__.py
tensordock/api.py
tensordock/exceptions.py
tensordock/endpoints/__init__.py
tensordock/endpoints/authorization.py
tensordock/endpoints/billing.py
tensordock/endpoints/containers.py
tensordock/endpoints/virtual_machines.py
tensordock-0.1.13.dist-info/METADATA
tensordock-0.1.13.dist-info/WHEEL
tensordock-0.1.13.dist-info/top_level.txt
tensordock-0.1.13.dist-info/RECORD
